bincheck.py
bincheck-2.0.4.dist-info/METADATA
bincheck-2.0.4.dist-info/WHEEL
bincheck-2.0.4.dist-info/top_level.txt
bincheck-2.0.4.dist-info/RECORD
