Metadata-Version: 2.1
Name: bincheck
Version: 2.0.4
Summary: Brentree Bin Refrence Check
Home-page: UNKNOWN
Author: doesntexit
Author-email: edwinhamal@gmail.com
License: UNKNOWN
Platform: UNKNOWN
Requires-Python: >=3.6
